LICENSE.AGPL.txt
LICENSE.BSD.txt
MANIFEST.in
README.md
requirements-docs.txt
requirements-test.txt
requirements.txt
setup.cfg
setup.py
Tornado_Restless.egg-info/PKG-INFO
Tornado_Restless.egg-info/SOURCES.txt
Tornado_Restless.egg-info/dependency_links.txt
Tornado_Restless.egg-info/requires.txt
Tornado_Restless.egg-info/top_level.txt
tornado_restless/__init__.py
tornado_restless/api.py
tornado_restless/convert.py
tornado_restless/errors.py
tornado_restless/handler.py
tornado_restless/wrapper.py