Metadata-Version: 1.1
Name: Tornado-Restless
Version: 0.4.5
Summary: flask-restless adopted for tornado
Home-page: https://github.com/tornado-utils/tornado-restless
Author: Martin Martimeo
Author-email: martin@martimeo.de
License: GNU AGPLv3+ or BSD-3-clause
Download-URL: https://github.com/tornado-utils/tornado-restless/tarball/0.4.5
Platform: any
Classifier: Development Status :: 4 - Beta
Classifier: Environment :: Web Environment
Classifier: License :: OSI Approved :: GNU Affero General Public License v3 or later (AGPLv3+)
Classifier: License :: OSI Approved :: BSD License
Classifier: Operating System :: OS Independent
Classifier: Programming Language :: Python
Classifier: Programming Language :: Python :: 3
Classifier: Programming Language :: Python :: 3.3
Classifier: Topic :: Software Development :: Libraries :: Python Modules
